uniteai/.dir-locals.el
uniteai/.uniteai.yml.example
uniteai/RELEASE.md
uniteai/__init__.py
uniteai/common.py
uniteai/config.py
uniteai/edit.py
uniteai/llm_server.py
uniteai/local_llm.py
uniteai/lsp_server.py
uniteai/openai.py
uniteai/transcription.py
uniteai/contrib/example.py
uniteai/contrib/text_to_speech.py
uniteai/document/README.md
uniteai/document/__init__.py
uniteai/document/download.py
uniteai/document/embed.py
uniteai-0.3.0.dist-info/METADATA
uniteai-0.3.0.dist-info/WHEEL
uniteai-0.3.0.dist-info/entry_points.txt
uniteai-0.3.0.dist-info/licenses/LICENSE
uniteai-0.3.0.dist-info/RECORD
