Metadata-Version: 2.1
Name: uniteai
Version: 0.3.0
Summary: AI, Inside your Editor.
Project-URL: Homepage, https://github.com/freckletonj/uniteai
Project-URL: Bug Tracker, https://github.com/freckletonj/uniteai/issues
Author: Josh Freckleton
License-Expression: Apache-2.0
License-File: LICENSE
Classifier: Operating System :: OS Independent
Classifier: Programming Language :: Python :: 3
Requires-Python: >=3.7
Requires-Dist: pygls
Requires-Dist: pyyaml
Requires-Dist: requests
Requires-Dist: thespian
Provides-Extra: all
Requires-Dist: accelerate; extra == 'all'
Requires-Dist: beautifulsoup4; extra == 'all'
Requires-Dist: bitsandbytes; extra == 'all'
Requires-Dist: einops; extra == 'all'
Requires-Dist: fastapi; extra == 'all'
Requires-Dist: gitpython; extra == 'all'
Requires-Dist: instructorembedding; extra == 'all'
Requires-Dist: nbformat; extra == 'all'
Requires-Dist: openai; extra == 'all'
Requires-Dist: openai-whisper; extra == 'all'
Requires-Dist: pandas; extra == 'all'
Requires-Dist: pyaudio; extra == 'all'
Requires-Dist: pypdf; extra == 'all'
Requires-Dist: scipy; extra == 'all'
Requires-Dist: sentence-transformers; extra == 'all'
Requires-Dist: sentencepiece; extra == 'all'
Requires-Dist: soundfile; extra == 'all'
Requires-Dist: speechrecognition; extra == 'all'
Requires-Dist: transformers; extra == 'all'
Requires-Dist: uvicorn; extra == 'all'
Requires-Dist: youtube-transcript-api; extra == 'all'
Provides-Extra: document-chat
Requires-Dist: beautifulsoup4; extra == 'document-chat'
Requires-Dist: gitpython; extra == 'document-chat'
Requires-Dist: instructorembedding; extra == 'document-chat'
Requires-Dist: nbformat; extra == 'document-chat'
Requires-Dist: pandas; extra == 'document-chat'
Requires-Dist: pypdf; extra == 'document-chat'
Requires-Dist: sentence-transformers; extra == 'document-chat'
Requires-Dist: youtube-transcript-api; extra == 'document-chat'
Provides-Extra: local-llm
Requires-Dist: accelerate; extra == 'local-llm'
Requires-Dist: bitsandbytes; extra == 'local-llm'
Requires-Dist: einops; extra == 'local-llm'
Requires-Dist: fastapi; extra == 'local-llm'
Requires-Dist: scipy; extra == 'local-llm'
Requires-Dist: sentencepiece; extra == 'local-llm'
Requires-Dist: transformers; extra == 'local-llm'
Requires-Dist: uvicorn; extra == 'local-llm'
Provides-Extra: openai
Requires-Dist: openai; extra == 'openai'
Provides-Extra: speech-to-text
Requires-Dist: sounddevice; extra == 'speech-to-text'
Requires-Dist: tts; extra == 'speech-to-text'
Provides-Extra: transcription
Requires-Dist: openai-whisper; extra == 'transcription'
Requires-Dist: pyaudio; extra == 'transcription'
Requires-Dist: soundfile; extra == 'transcription'
Requires-Dist: speechrecognition; extra == 'transcription'
